pyliseberg/__init__.py
pyliseberg-1.0.dist-info/METADATA
pyliseberg-1.0.dist-info/RECORD
pyliseberg-1.0.dist-info/WHEEL
pyliseberg-1.0.dist-info/top_level.txt
